<?xml version="1.0" encoding="UTF-8"?>
<sensor name = "canonT5i" fileformat = "PNG">
  <physical focallength="55" sensorWidth = "22.3"/>
  <resolution x = "5184" y = "3456"/>
  <principalPoint x = "2592" y="1728"/>
  <blender compression = "100" percentage = "100" antialiasing = "0"/>
    <postprocessing>
    <distortion k1 = "0" k2 = "0" k3 = "0" k4 = "0" p1 = "0" p2 = "0" isPhotoscanUnits = "1"/>
    <vignetting v1 = "0" v2 = "0" />
    <saltnoise prob = "0.01"/>
    <peppernoise prob = "0"/>
    <gaussiannoise mean = "0" variance = "0"/>
    <gaussianblur sigma = "0"/>
  </postprocessing>
</sensor>